{
  "format_version": "1.21.0",
  "minecraft:item": {
    "description": {
      "identifier": "feather:invisible_potion"
    },

    "components": {
      "minecraft:display_name": {
        "value": "透明化のポーション"
      },
      "minecraft:icon": "invisible_potion",
      "minecraft:max_stack_size": 1,
      "minecraft:glint": true,

      "minecraft:food": {
        "can_always_eat": true,
        "nutrition": 0,
        "saturation_modifier": 0
      },
      "minecraft:use_animation": "drink",
      "minecraft:use_modifiers": {
        "movement_modifier": 0,
        "use_duration": 3
      }
    }
  }
}